[
 {
   "First_Name": "John",
   "Last_name": "Doe",
   "Street": "120 jefferson, st.",
   "City": "Riverside", 
   "Province": " NJ",
   "PinCode": 8075,
   "Date": "11/9/2023"
 },
 {
   "First_Name": "Jack",
   "Last_name": "McGinnis",
   "Street": "220 hobo Av.",
   "City": "Phila",
   "Province": " PA",
   "PinCode": 9119,
   "Date": "11/9/2023"
 },
 {
   "First_Name": "John Da Man",
   "Last_name": "Repici",
   "Street": "120 Jefferson St.",
   "City": "Riverside",
   "Province": " NJ",
   "PinCode": 8075,
   "Date": "11/9/2023"
 },
 {
   "First_Name": "Stephen",
   "Last_name": "Tyler",
   "Street": "7452 Terrace At the Plaza road",
   "City": "SomeTown",
   "Province": "SD",
   "PinCode": 91234,
   "Date": "11/9/2023"
 },
 {
   "First_Name": "",
   "Last_name": "Blankman",
   "Street": "",
   "City": "SomeTown",
   "Province": " SD",
   "PinCode": 298,
   "Date": "11/9/2023"
 },
 {
   "First_Name": "Joan the bone, Anne",
   "Last_name": "Jet",
   "Street": "9th, at Terrace plc",
   "City": "Desert City",
   "Province": "CO",
   "PinCode": 123,
   "Date": "11/9/2023"
 }
]